Nanoha/__init__.py
Nanoha/pyplot/__init__.py
Nanoha/pyplot/mollweide.py
Nanoha-1.0.2.dist-info/METADATA
Nanoha-1.0.2.dist-info/WHEEL
Nanoha-1.0.2.dist-info/top_level.txt
Nanoha-1.0.2.dist-info/RECORD
